crabflow-0.1.0.dist-info/METADATA
crabflow-0.1.0.dist-info/WHEEL
crabflow/__init__.py
crabflow/crabflow.cpython-310-darwin.so
crabflow-0.1.0.dist-info/RECORD
