Metadata-Version: 2.3
Name: crabflow
Version: 0.1.0
Summary: Task orchestrator.
Author: Guillaune Leroy <pro.guillaume.leroy@gmail.com>
Author-email: Guillaune Leroy <pro.guillaume.leroy@gmail.com>
License: MIT
Project-URL: Source Code, https://github.com/leroyguillaume/crabflow
